pdf2html_ai/__init__.py
pdf2html_ai/html_converter.py
pdf2html_ai/image_handler.py
pdf2html_ai/processor.py
pdf2html_ai/utils.py
pdf2html_ai-0.1.3.dist-info/LICENSE
pdf2html_ai-0.1.3.dist-info/METADATA
pdf2html_ai-0.1.3.dist-info/WHEEL
pdf2html_ai-0.1.3.dist-info/entry_points.txt
pdf2html_ai-0.1.3.dist-info/top_level.txt
pdf2html_ai-0.1.3.dist-info/RECORD
