Metadata-Version: 2.2
Name: pdf2html-ai
Version: 0.1.3
Summary: AI-powered PDF to HTML conversion using mistral-ocr and pixtral-12b
Home-page: https://github.com/yourusername/pdf2html_ai
Author: Mystique
Author-email: mystique@tuta.com
Classifier: Programming Language :: Python :: 3
Classifier: License :: OSI Approved :: MIT License
Classifier: Operating System :: OS Independent
Requires-Python: >=3.10
License-File: LICENSE
Requires-Dist: mistralai
Requires-Dist: python-dotenv
Requires-Dist: requests
Requires-Dist: PyPDF2
Dynamic: author
Dynamic: author-email
Dynamic: classifier
Dynamic: description
Dynamic: description-content-type
Dynamic: home-page
Dynamic: requires-dist
Dynamic: requires-python
Dynamic: summary
